oneping/__init__.py
oneping/__main__.py
oneping/api.py
oneping/chat.py
oneping/curl.py
oneping/providers.py
oneping/server.py
oneping/utils.py
oneping/interface/fasthtml.py
oneping/interface/textual.py
oneping/interface/web/fasthtml.css
oneping/interface/web/fasthtml.js
oneping/native/__init__.py
oneping/native/anthropic.py
oneping/native/fireworks.py
oneping/native/groq.py
oneping/native/openai.py
oneping-0.5.7.dist-info/LICENSE
oneping-0.5.7.dist-info/METADATA
oneping-0.5.7.dist-info/WHEEL
oneping-0.5.7.dist-info/entry_points.txt
oneping-0.5.7.dist-info/top_level.txt
oneping-0.5.7.dist-info/RECORD
