Metadata-Version: 2.1
Name: oneping
Version: 0.5.7
Summary: LLM provider abstraction layer.
Author-email: Doug Hanley <doug@compendiumlabs.ai>
License: MIT
Project-URL: Homepage, http://github.com/CompendiumLabs/oneping
Keywords: llm,chat
Classifier: License :: OSI Approved :: MIT License
Classifier: Programming Language :: Python
Classifier: Programming Language :: Python :: 3
Requires-Python: >=3.7
License-File: LICENSE
Requires-Dist: aiohttp
Requires-Dist: fire
Provides-Extra: chat
Requires-Dist: asyncstdlib ; extra == 'chat'
Requires-Dist: textual ; extra == 'chat'
Requires-Dist: python-fasthtml ; extra == 'chat'
Provides-Extra: native
Requires-Dist: openai ; extra == 'native'
Requires-Dist: anthropic ; extra == 'native'
Requires-Dist: fireworks-ai ; extra == 'native'
